{
    "2": [
        [
            -7256,
            1,
            1
        ],
        [
            1
        ],
        [
            248,
            1
        ]
    ],
    "3": [
        [
            -24528,
            -2348,
            0,
            1
        ],
        [
            42,
            1
        ],
        [
            234,
            1
        ]
    ],
    "5": [
        [
            449408,
            73056,
            -3800,
            -670,
            0,
            1
        ],
        [
            1
        ],
        [
            3856,
            248,
            1
        ]
    ],
    "7": [
        [
            -2128500,
            -186955,
            204792,
            31647,
            -1428,
            -357,
            0,
            1
        ],
        [
            81,
            18,
            1
        ],
        [
            2545,
            242,
            1
        ]
    ],
    "11": [
        [
            8720000,
            19849600,
            8252640,
            -1867712,
            -1675784,
            -184184,
            57442,
            11440,
            -506,
            -187,
            0,
            1
        ],
        [
            1
        ],
        [
            38800,
            21920,
            4056,
            248,
            1
        ]
    ],
    "13": [
        [
            -24576000,
            -32384000,
            5859360,
            23669490,
            9614956,
            -700323,
            -1161420,
            -149786,
            37596,
            8502,
            -364,
            -156,
            0,
            1
        ],
        [
            9,
            6,
            1
        ],
        [
            25600,
            16800,
            3577,
            246,
            1
        ]
    ],
    "17": [
        [
            25608112,
            128884056,
            169635044,
            18738794,
            -125706976,
            -98725154,
            -13049914,
            16023299,
            7118240,
            -70737,
            -630836,
            -91766,
            20808,
            5338,
            -238,
            -119,
            0,
            1
        ],
        [
            1
        ],
        [
            73252,
            122444,
            80561,
            25988,
            4082,
            248,
            1
        ]
    ],
    "19": [
        [
            -24576000,
            -90675200,
            -51363840,
            196605312,
            358921248,
            190349904,
            -54954270,
            -101838024,
            -30202704,
            9356265,
            6935646,
            444030,
            -519042,
            -97983,
            16416,
            5073,
            -190,
            -114,
            0,
            1
        ],
        [
            9,
            6,
            1
        ],
        [
            25600,
            57280,
            48544,
            19312,
            3593,
            246,
            1
        ]
    ],
    "23": [
        [
            -65536,
            -516096,
            -1648640,
            -2213888,
            1554432,
            11787776,
            21906304,
            19783680,
            3833824,
            -11002464,
            -11625488,
            -2882544,
            2689666,
            1978368,
            -19136,
            -393024,
            -53084,
            46644,
            5681,
            -3864,
            0,
            161,
            -23,
            1
        ],
        [
            1
        ],
        [
            1024,
            5376,
            12992,
            18432,
            16224,
            8352,
            2384,
            240,
            1
        ]
    ],
    "29": [
        [
            -6750,
            -12150,
            281880,
            570024,
            -1754181,
            -5229135,
            2357613,
            19103721,
            9708910,
            -31795426,
            -38397537,
            19207947,
            54103270,
            9216142,
            -37142939,
            -18871083,
            14041394,
            10954634,
            -3592085,
            -3427365,
            853818,
            622398,
            -189399,
            -53679,
            26680,
            -580,
            -1421,
            319,
            -29,
            1
        ],
        [
            1
        ],
        [
            225,
            270,
            459,
            -744,
            -3707,
            -1730,
            3365,
            4072,
            1907,
            238,
            1
        ]
    ],
    "31": [
        [
            -65536,
            286720,
            2095104,
            -10856448,
            -952320,
            72423936,
            -73848448,
            -188170496,
            329047392,
            217998944,
            -668209712,
            -57343056,
            790720162,
            -145826728,
            -591434244,
            202591944,
            285180966,
            -132017220,
            -86008539,
            51887118,
            14248995,
            -12762049,
            -513701,
            1863906,
            -245768,
            -130975,
            41571,
            31,
            -1891,
            372,
            -31,
            1
        ],
        [
            1,
            -2,
            1
        ],
        [
            1024,
            -2304,
            448,
            4096,
            -2208,
            -5088,
            272,
            3600,
            1905,
            238,
            1
        ]
    ],
    "41": [
        [
            16000,
            67200,
            -465760,
            -2966432,
            -1742664,
            20985112,
            46140990,
            -31732934,
            -217030548,
            -147139488,
            436080674,
            745775322,
            -271341362,
            -1542677562,
            -605560447,
            1832223375,
            1772593672,
            -1270633050,
            -2400692229,
            343522723,
            2179745361,
            282422801,
            -1503727029,
            -421357697,
            879637411,
            261059095,
            -462271351,
            -61715127,
            193718727,
            -24135265,
            -49355103,
            20512341,
            3613289,
            -4706595,
            1099661,
            163057,
            -162483,
            46617,
            -7544,
            738,
            -41,
            1
        ],
        [
            1
        ],
        [
            400,
            1120,
            -184,
            -672,
            2361,
            -2926,
            -7733,
            3040,
            9101,
            -1006,
            -2659,
            -1896,
            963,
            234,
            1
        ]
    ],
    "47": [
        [
            -65536,
            688128,
            -2502656,
            -96256,
            38598656,
            -187217920,
            508021120,
            -845669120,
            552981696,
            1469334304,
            -5945275904,
            11705275552,
            -14673798654,
            9100068184,
            8421580132,
            -34288012648,
            56657584158,
            -60426283952,
            36612252089,
            9942017442,
            -60791892299,
            93046207239,
            -92028642340,
            59196883097,
            -10454018992,
            -33364599371,
            57280402355,
            -57873890484,
            41879296232,
            -20241250112,
            2065827049,
            8435506655,
            -11611941072,
            10182603298,
            -7040645261,
            4071881378,
            -2013138357,
            856757031,
            -313468474,
            97893151,
            -25770006,
            5617769,
            -990431,
            136864,
            -14194,
            1034,
            -47,
            1
        ],
        [
            1
        ],
        [
            1024,
            -7168,
            25024,
            -57984,
            102656,
            -143584,
            163968,
            -152864,
            120769,
            -76312,
            43644,
            -17480,
            7814,
            -1032,
            508,
            232,
            1
        ]
    ],
    "59": [
        [
            16000,
            -67200,
            -783520,
            5573376,
            -5127336,
            -60792184,
            241324042,
            -170978932,
            -1262437160,
            4310971231,
            -3953349811,
            -10887235780,
            41679530185,
            -51342089572,
            -33068562195,
            230682514316,
            -372641172307,
            121615007703,
            682044179678,
            -1549365239197,
            1373184591667,
            614906882627,
            -3566756201696,
            4920423266916,
            -2342393877496,
            -3589340274442,
            8772457933356,
            -8488557160148,
            1742977715620,
            7131088674129,
            -11643540780203,
            8512399456274,
            -315658868113,
            -6917286294515,
            8713332734648,
            -5190227733987,
            -54249978263,
            3397583328372,
            -3658171840037,
            1987950394792,
            -179519591637,
            -748989116551,
            800595050760,
            -459184355769,
            134398080099,
            28871590941,
            -64236756338,
            46651654354,
            -23352309386,
            9059054346,
            -2830320860,
            721829600,
            -150487052,
            25475079,
            -3452149,
            365800,
            -29205,
            1652,
            -59,
            1
        ],
        [
            1
        ],
        [
            400,
            -1120,
            -776,
            3144,
            4945,
            -10532,
            -23442,
            82400,
            -74383,
            -45208,
            195830,
            -267564,
            241876,
            -170700,
            100862,
            -48352,
            16417,
            -2584,
            -418,
            228,
            1
        ]
    ],
    "71": [
        [
            -6750,
            97200,
            -603855,
            2263977,
            -4854483,
            -2486349,
            75190491,
            -399596520,
            1441975423,
            -4089818964,
            9450153463,
            -17516526653,
            23635982289,
            -11859874932,
            -53385529273,
            230566737711,
            -585283867605,
            1136695427037,
            -1753961304140,
            2020891913264,
            -1147488305875,
            -1930304898882,
            8102336330029,
            -17218530732347,
            27006964902986,
            -32365758791872,
            25902000374138,
            -468390635342,
            -46332664858222,
            107139839089502,
            -162234735929274,
            182582147217312,
            -140033523896938,
            22513210292184,
            152367877270246,
            -334009986053250,
            451855980915164,
            -443144048889720,
            284518400252142,
            -11142427766850,
            -289840331821002,
            512373447321402,
            -576967281819172,
            466024421705696,
            -230395084854230,
            -36287337331916,
            241209603962570,
            -330646545417814,
            304702155703516,
            -205131886553392,
            87504290135653,
            5131997859077,
            -54867900326127,
            66216047255551,
            -54817285755105,
            36239054778472,
            -20052219750661,
            9464634765852,
            -3841191816845,
            1343947848527,
            -405138280373,
            104923131180,
            -23228729413,
            4364552115,
            -689157169,
            90223321,
            -9613968,
            812240,
            -52327,
            2414,
            -71,
            1
        ],
        [
            1
        ],
        [
            225,
            -2160,
            9936,
            -33576,
            98512,
            -235776,
            501596,
            -935728,
            1540528,
            -2289208,
            3051056,
            -3629088,
            3886438,
            -3727056,
            3130928,
            -2256088,
            1376816,
            -714688,
            319068,
            -115088,
            25936,
            -456,
            -1328,
            224,
            1
        ]
    ]
}